odoo10_addon_account_cash_discount_write_off-10.0.1.0.0.99.dev7-py2.7-nspkg.pth
odoo/addons/account_cash_discount_write_off/README.rst
odoo/addons/account_cash_discount_write_off/__init__.py
odoo/addons/account_cash_discount_write_off/__manifest__.py
odoo/addons/account_cash_discount_write_off/i18n/account_cash_discount_write_off.pot
odoo/addons/account_cash_discount_write_off/i18n/fr.po
odoo/addons/account_cash_discount_write_off/models/__init__.py
odoo/addons/account_cash_discount_write_off/models/account_payment_line.py
odoo/addons/account_cash_discount_write_off/models/account_payment_order.py
odoo/addons/account_cash_discount_write_off/models/res_company.py
odoo/addons/account_cash_discount_write_off/static/description/icon.png
odoo/addons/account_cash_discount_write_off/tests/__init__.py
odoo/addons/account_cash_discount_write_off/tests/test_account_cash_discount_write_off.py
odoo/addons/account_cash_discount_write_off/views/res_company.xml
odoo10_addon_account_cash_discount_write_off-10.0.1.0.0.99.dev7.dist-info/METADATA
odoo10_addon_account_cash_discount_write_off-10.0.1.0.0.99.dev7.dist-info/RECORD
odoo10_addon_account_cash_discount_write_off-10.0.1.0.0.99.dev7.dist-info/WHEEL
odoo10_addon_account_cash_discount_write_off-10.0.1.0.0.99.dev7.dist-info/namespace_packages.txt
odoo10_addon_account_cash_discount_write_off-10.0.1.0.0.99.dev7.dist-info/top_level.txt
