Metadata-Version: 2.1
Name: odoo10-addon-account-cash-discount-write-off
Version: 10.0.1.0.0.99.dev7
Summary: Create an automatic writeoff for payment with discount on the payment
Home-page: https://github.com/acsone/account-payment
Author: ACSONE SA/NV, Odoo Community Association (OCA)
Author-email: support@odoo-community.org
License: AGPL-3
Platform: UNKNOWN
Classifier: Programming Language :: Python
Classifier: Framework :: Odoo
Classifier: License :: OSI Approved :: GNU Affero General Public License v3
Requires-Python: ~=2.7
Requires-Dist: odoo10-addon-account-cash-discount-payment
Requires-Dist: odoo (<10.1dev,>=10.0)
